django_on_heroku/__init__.py
django_on_heroku/__version__.py
django_on_heroku/core.py
django_on_heroku-1.1.2.dist-info/LICENSE
django_on_heroku-1.1.2.dist-info/METADATA
django_on_heroku-1.1.2.dist-info/WHEEL
django_on_heroku-1.1.2.dist-info/top_level.txt
django_on_heroku-1.1.2.dist-info/RECORD
